{"type":"FeatureCollection","features":[{"type":"Feature","geometry":{"type":"Point","coordinates":[-1.544227,53.797563]},"properties":{"name":"Leeds","country":"United Kingdom","county":"Leeds","datasource":{"sourcename":"whosonfirst","url":"https://www.whosonfirst.org/docs/licenses/"},"country_code":"gb","state":"West Yorkshire","city":"Leeds","lon":-1.544227,"lat":53.797563,"formatted":"Leeds, West Yorkshire, United Kingdom","address_line1":"Leeds","address_line2":"West Yorkshire, United Kingdom","result_type":"city","rank":{"popularity":8.988490181891963,"confidence":1,"match_type":"full_match"},"place_id":"51639ae95e27b5f8bf59f4bf5c8b16e64a40"},"bbox":[-1.80035825457,53.6989793785,-1.35860819857,53.8968853952]},{"type":"Feature","geometry":{"type":"Point","coordinates":[0.605843,51.246742]},"properties":{"name":"Leeds","country":"United Kingdom","county":"Kent","datasource":{"sourcename":"whosonfirst","url":"https://www.whosonfirst.org/docs/licenses/"},"country_code":"gb","state":"Kent","district":"Leeds","city":"Leeds","lon":0.605843,"lat":51.246742,"formatted":"Leeds, Kent, United Kingdom","address_line1":"Leeds","address_line2":"Kent, United Kingdom","result_type":"city","rank":{"popularity":4.976760489590618,"confidence":1,"match_type":"full_match"},"place_id":"513f56f0db1063e33f595a46ea3d959f4940"},"bbox":[0.580347224916,51.2319477069,0.628957286446,51.2624336414]}],"bbox":[-1.80035825457,51.2319477069,0.628957286446,53.8968853952],"query":{"text":"Leeds","parsed":{"city":"leeds","expected_type":"city"}}}